[
    {
        "butikk": "Tuesday",
        "Klient": 7,
        "mmoms": " 575 730 kr",
        "umoms": " 460 584 kr",
        "db": " 112 121 kr",
        "dg": "24.3 %",
        "antord": 491,
        "prord": " 1 173 kr"
    },
    {
        "butikk": "Wednesday",
        "Klient": 7,
        "mmoms": " 659 061 kr",
        "umoms": " 527 249 kr",
        "db": " 96 842 kr",
        "dg": "18.4 %",
        "antord": 469,
        "prord": " 1 405 kr"
    },
    {
        "butikk": "Thursday",
        "Klient": 7,
        "mmoms": " 630 772 kr",
        "umoms": " 504 617 kr",
        "db": " 101 826 kr",
        "dg": "20.2 %",
        "antord": 454,
        "prord": " 1 389 kr"
    },
    {
        "butikk": "Friday",
        "Klient": 7,
        "mmoms": " 447 661 kr",
        "umoms": " 358 129 kr",
        "db": " 88 058 kr",
        "dg": "24.6 %",
        "antord": 306,
        "prord": " 1 463 kr"
    },
    {
        "butikk": "Saturday",
        "Klient": 7,
        "mmoms": " 456 649 kr",
        "umoms": " 365 319 kr",
        "db": " 82 213 kr",
        "dg": "22.5 %",
        "antord": 397,
        "prord": " 1 150 kr"
    }
]