[{"butikk":"Skien","mmoms":"-8 891 882 kr","umoms":"-7 113 506 kr","db":"-3 120 804 kr","dg":"-3.3%","antord":"-  315","prord":"-  173 kr"},{"butikk":"Kristiansand","mmoms":"-22 362 802 kr","umoms":"-17 890 242 kr","db":"-4 445 437 kr","dg":"-4.8%","antord":"- 17 021","prord":"  16 kr"},{"butikk":"Tønsberg","mmoms":"- 261 106 kr","umoms":"- 208 885 kr","db":"- 851 762 kr","dg":"-2.0%","antord":"  227","prord":"-  12 kr"},{"butikk":"Arendal","mmoms":"1 148 638 kr","umoms":" 918 911 kr","db":"-1 603 762 kr","dg":"-3.6%","antord":" 2 128","prord":"-  24 kr"},{"butikk":"Sandefjord","mmoms":" 453 600 kr","umoms":" 362 880 kr","db":"- 927 313 kr","dg":"-3.2%","antord":"-  363","prord":"  24 kr"},{"butikk":"Larvik","mmoms":"1 811 732 kr","umoms":"1 449 385 kr","db":"- 286 059 kr","dg":"-2.4%","antord":"  385","prord":"  51 kr"},{"butikk":"Totalt","mmoms":"-37 858 193 kr","umoms":"-30 286 554 kr","db":"-12 767 755 kr","dg":"-3.0%","antord":"- 37 802","prord":"  35 kr"}]
