[{"butikk":"Brødr. Berg Stenindustri AS avd. Skien","mmoms":"3 790 277 kr","umoms":"3 032 222 kr","antord":" 2 022","prord":"  50 kr"},{"butikk":"Brødr. Berg Stenindustri AS avd. Porsgrunn","mmoms":"-1 556 981 kr","umoms":"-1 245 585 kr","antord":"-  524","prord":"-  179 kr"},{"butikk":"Megaflis Sørlandsparken AS","mmoms":"1 968 428 kr","umoms":"1 574 742 kr","antord":" 1 968","prord":"-  50 kr"},{"butikk":"Megaflis Tønsberg AS","mmoms":"-2 202 236 kr","umoms":"-1 761 789 kr","antord":"- 3 051","prord":"  70 kr"},{"butikk":"Megaflis Agderparken AS","mmoms":"5 751 906 kr","umoms":"4 601 525 kr","antord":" 4 430","prord":"  17 kr"},{"butikk":"Megaflis Sandefjord AS","mmoms":"1 372 983 kr","umoms":"1 098 386 kr","antord":"  487","prord":"  57 kr"},{"butikk":"Megaflis Larvik AS","mmoms":"2 337 886 kr","umoms":"1 870 309 kr","antord":" 1 238","prord":"  85 kr"},{"butikk":"Totalt","mmoms":"11 462 262 kr","umoms":"9 169 810 kr","antord":" 6 570","prord":"  33 kr"}]
