[{"butikk":"Brødr. Berg Stenindustri AS avd. Skien","mmoms":"4 964 039 kr","umoms":"3 971 231 kr","antord":" 2 517","prord":"  67 kr"},{"butikk":"Brødr. Berg Stenindustri AS avd. Porsgrunn","mmoms":"-1 707 789 kr","umoms":"-1 366 231 kr","antord":"-  596","prord":"-  170 kr"},{"butikk":"Megaflis Sørlandsparken AS","mmoms":"2 108 979 kr","umoms":"1 687 183 kr","antord":" 2 259","prord":"-  58 kr"},{"butikk":"Megaflis Tønsberg AS","mmoms":"-1 429 442 kr","umoms":"-1 143 553 kr","antord":"- 2 609","prord":"  75 kr"},{"butikk":"Megaflis Agderparken AS","mmoms":"6 356 075 kr","umoms":"5 084 860 kr","antord":" 5 137","prord":"  7 kr"},{"butikk":"Megaflis Sandefjord AS","mmoms":"1 843 203 kr","umoms":"1 474 563 kr","antord":"  743","prord":"  62 kr"},{"butikk":"Megaflis Larvik AS","mmoms":"3 057 128 kr","umoms":"2 445 702 kr","antord":" 1 554","prord":"  105 kr"},{"butikk":"Totalt","mmoms":"15 193 790 kr","umoms":"12 155 032 kr","antord":" 9 006","prord":"  36 kr"}]
