[{"butikk":"Skien","mmoms":"-89 275 127 kr","umoms":"-71 420 102 kr","db":"-17 851 231 kr","dg":"-2.4%","antord":"- 69 967","prord":"  102 kr"},{"butikk":"Porsgrunn","mmoms":"-24 417 886 kr","umoms":"-19 534 309 kr","db":"-4 546 292 kr","dg":"-2.5%","antord":"- 26 736","prord":"-  75 kr"},{"butikk":"Kristiansand","mmoms":"-63 897 136 kr","umoms":"-51 117 709 kr","db":"-13 353 476 kr","dg":"-3.6%","antord":"- 51 721","prord":"  55 kr"},{"butikk":"Tønsberg","mmoms":"-78 835 940 kr","umoms":"-63 068 752 kr","db":"-16 515 110 kr","dg":"-3.4%","antord":"- 73 859","prord":"  63 kr"},{"butikk":"Arendal","mmoms":"-87 458 515 kr","umoms":"-69 966 812 kr","db":"-18 580 244 kr","dg":"-3.1%","antord":"- 77 277","prord":"  19 kr"},{"butikk":"Sandefjord","mmoms":"-61 670 652 kr","umoms":"-49 336 522 kr","db":"-13 481 567 kr","dg":"-3.7%","antord":"- 57 502","prord":"  3 kr"},{"butikk":"Larvik","mmoms":"-45 017 314 kr","umoms":"-36 013 851 kr","db":"-9 181 912 kr","dg":"-2.4%","antord":"- 36 582","prord":"-  100 kr"},{"butikk":"Totalt","mmoms":"-450 567 807 kr","umoms":"-360 454 245 kr","db":"-93 509 603 kr","dg":"-3.1%","antord":"- 341 143","prord":"-  72 kr"}]
