[{"butikk":"Brødr. Berg Stenindustri AS avd. Skien","mmoms":"1 303 145 kr","umoms":"1 042 516 kr","db":" 247 770 kr","dg":"0.09%","antord":"  841","prord":"  5 kr"},{"butikk":"Brødr. Berg Stenindustri AS avd. Porsgrunn","mmoms":"- 279 474 kr","umoms":"- 223 579 kr","db":"- 85 537 kr","dg":"-2.71%","antord":"  116","prord":"-  232 kr"},{"butikk":"Megaflis Sørlandsparken AS","mmoms":" 845 277 kr","umoms":" 676 222 kr","db":" 164 065 kr","dg":"0.11%","antord":"  657","prord":"-  29 kr"},{"butikk":"Megaflis Tønsberg AS","mmoms":" 194 238 kr","umoms":" 155 390 kr","db":" 113 628 kr","dg":"1.43%","antord":"-  74","prord":"  49 kr"},{"butikk":"Megaflis Agderparken AS","mmoms":"2 110 813 kr","umoms":"1 688 650 kr","db":" 419 985 kr","dg":"0.18%","antord":" 1 265","prord":"  73 kr"},{"butikk":"Megaflis Sandefjord AS","mmoms":" 925 276 kr","umoms":" 740 220 kr","db":" 134 675 kr","dg":"-1.21%","antord":"  530","prord":"  75 kr"},{"butikk":"Megaflis Larvik AS","mmoms":" 696 124 kr","umoms":" 556 899 kr","db":" 146 251 kr","dg":"0.41%","antord":"  534","prord":"-  5 kr"},{"butikk":"Totalt","mmoms":"5 795 399 kr","umoms":"4 636 319 kr","db":"1 140 838 kr","dg":"0.15%","antord":" 3 869","prord":"  24 kr"}]
