[{"butikk":"Brødr. Berg Stenindustri AS avd. Skien","mmoms":"8 912 125 kr","umoms":"7 129 700 kr","antord":" 5 283","prord":"  37 kr"},{"butikk":"Brødr. Berg Stenindustri AS avd. Porsgrunn","mmoms":"-3 076 228 kr","umoms":"-2 460 982 kr","antord":"- 1 277","prord":"-  119 kr"},{"butikk":"Megaflis Sørlandsparken AS","mmoms":"4 224 368 kr","umoms":"3 379 494 kr","antord":" 3 439","prord":"-  4 kr"},{"butikk":"Megaflis Tønsberg AS","mmoms":"-1 627 309 kr","umoms":"-1 301 847 kr","antord":"- 4 203","prord":"  63 kr"},{"butikk":"Megaflis Agderparken AS","mmoms":"10 947 020 kr","umoms":"8 757 616 kr","antord":" 9 091","prord":"  9 kr"},{"butikk":"Megaflis Sandefjord AS","mmoms":"3 997 516 kr","umoms":"3 198 013 kr","antord":" 1 811","prord":"  53 kr"},{"butikk":"Megaflis Larvik AS","mmoms":"6 059 613 kr","umoms":"4 847 691 kr","antord":" 3 461","prord":"  77 kr"},{"butikk":"Totalt","mmoms":"29 437 106 kr","umoms":"23 549 685 kr","antord":" 17 605","prord":"  33 kr"}]
