[{"butikk":"Brødr. Berg Stenindustri AS avd. Skien","mmoms":" 984 344 kr","umoms":" 787 475 kr","db":" 168 729 kr","dg":"-0.20%","antord":"  641","prord":"  0 kr"},{"butikk":"Brødr. Berg Stenindustri AS avd. Porsgrunn","mmoms":"- 340 794 kr","umoms":"- 272 635 kr","db":"- 96 434 kr","dg":"-2.99%","antord":"  56","prord":"-  256 kr"},{"butikk":"Megaflis Sørlandsparken AS","mmoms":" 729 442 kr","umoms":" 583 553 kr","db":" 134 765 kr","dg":"-0.05%","antord":"  554","prord":"-  22 kr"},{"butikk":"Megaflis Tønsberg AS","mmoms":" 8 575 kr","umoms":" 6 860 kr","db":" 44 408 kr","dg":"0.85%","antord":"-  236","prord":"  55 kr"},{"butikk":"Megaflis Agderparken AS","mmoms":"1 739 807 kr","umoms":"1 391 845 kr","db":" 317 390 kr","dg":"-0.32%","antord":"  985","prord":"  74 kr"},{"butikk":"Megaflis Sandefjord AS","mmoms":" 750 610 kr","umoms":" 600 488 kr","db":" 107 010 kr","dg":"-1.11%","antord":"  413","prord":"  69 kr"},{"butikk":"Megaflis Larvik AS","mmoms":" 471 944 kr","umoms":" 377 555 kr","db":" 91 829 kr","dg":"0.07%","antord":"  394","prord":"-  22 kr"},{"butikk":"Totalt","mmoms":"4 343 927 kr","umoms":"3 475 142 kr","db":" 767 698 kr","dg":"-0.17%","antord":" 2 807","prord":"  22 kr"}]
