[{"butikk":"Brødr. Berg Stenindustri AS avd. Skien","ERPHostCompanyNo":1,"WarehouseNo":1,"mmoms":"11 590 415 kr","umoms":"9 272 332 kr","db":"2 181 071 kr","dg":"23.52%","antord":" 7 716","prord":" 1 502 kr"},{"butikk":"Brødr. Berg Stenindustri AS avd. Porsgrunn","ERPHostCompanyNo":1,"WarehouseNo":2,"mmoms":"2 008 956 kr","umoms":"1 607 164 kr","db":" 351 767 kr","dg":"21.89%","antord":" 2 291","prord":"  877 kr"},{"butikk":"Megaflis Sørlandsparken AS","ERPHostCompanyNo":2,"WarehouseNo":1,"mmoms":"7 899 563 kr","umoms":"6 319 650 kr","db":"1 561 439 kr","dg":"24.71%","antord":" 5 522","prord":" 1 431 kr"},{"butikk":"Megaflis Tønsberg AS","ERPHostCompanyNo":3,"WarehouseNo":1,"mmoms":"8 755 050 kr","umoms":"7 004 040 kr","db":"1 722 777 kr","dg":"24.60%","antord":" 7 444","prord":" 1 176 kr"},{"butikk":"Megaflis Agderparken AS","ERPHostCompanyNo":4,"WarehouseNo":1,"mmoms":"11 054 904 kr","umoms":"8 843 923 kr","db":"2 209 769 kr","dg":"24.99%","antord":" 8 330","prord":" 1 327 kr"},{"butikk":"Megaflis Sandefjord AS","ERPHostCompanyNo":10,"WarehouseNo":1,"mmoms":"6 632 749 kr","umoms":"5 306 199 kr","db":"1 330 799 kr","dg":"25.08%","antord":" 5 588","prord":" 1 187 kr"},{"butikk":"Megaflis Larvik AS","ERPHostCompanyNo":16,"WarehouseNo":1,"mmoms":"5 154 099 kr","umoms":"4 123 279 kr","db":"1 014 313 kr","dg":"24.60%","antord":" 4 002","prord":" 1 288 kr"},{"butikk":"Totalt","ERPHostCompanyNo":9999,"WarehouseNo":9999,"mmoms":"53 095 737 kr","umoms":"42 476 589 kr","db":"10 371 935 kr","dg":"24.42%","antord":" 40 893","prord":" 1 298 kr"}]
