[{"butikk":"Brødr. Berg Stenindustri AS avd. Skien","ERPHostCompanyNo":1,"WarehouseNo":1,"mmoms":"26 627 177 kr","umoms":"21 301 741 kr","antord":" 18 188","prord":" 1 464 kr"},{"butikk":"Brødr. Berg Stenindustri AS avd. Porsgrunn","ERPHostCompanyNo":1,"WarehouseNo":2,"mmoms":"4 452 258 kr","umoms":"3 561 807 kr","antord":" 5 351","prord":"  832 kr"},{"butikk":"Megaflis Sørlandsparken AS","ERPHostCompanyNo":2,"WarehouseNo":1,"mmoms":"18 409 328 kr","umoms":"14 727 462 kr","antord":" 13 971","prord":" 1 318 kr"},{"butikk":"Megaflis Tønsberg AS","ERPHostCompanyNo":3,"WarehouseNo":1,"mmoms":"19 266 383 kr","umoms":"15 413 107 kr","antord":" 16 042","prord":" 1 201 kr"},{"butikk":"Megaflis Agderparken AS","ERPHostCompanyNo":4,"WarehouseNo":1,"mmoms":"27 137 466 kr","umoms":"21 709 972 kr","antord":" 21 971","prord":" 1 235 kr"},{"butikk":"Megaflis Sandefjord AS","ERPHostCompanyNo":10,"WarehouseNo":1,"mmoms":"15 957 611 kr","umoms":"12 766 089 kr","antord":" 13 555","prord":" 1 177 kr"},{"butikk":"Megaflis Larvik AS","ERPHostCompanyNo":16,"WarehouseNo":1,"mmoms":"12 261 821 kr","umoms":"9 809 457 kr","antord":" 9 495","prord":" 1 291 kr"},{"butikk":"Totalt","ERPHostCompanyNo":9999,"WarehouseNo":9999,"mmoms":"124 112 044 kr","umoms":"99 289 635 kr","antord":" 98 573","prord":" 1 259 kr"}]
