[{"butikk":"Brødr. Berg Stenindustri AS avd. Skien","ERPHostCompanyNo":1,"WarehouseNo":1,"mmoms":"32 779 501 kr","umoms":"26 223 601 kr","antord":" 22 679","prord":" 1 445 kr"},{"butikk":"Brødr. Berg Stenindustri AS avd. Porsgrunn","ERPHostCompanyNo":1,"WarehouseNo":2,"mmoms":"5 556 787 kr","umoms":"4 445 430 kr","antord":" 6 733","prord":"  825 kr"},{"butikk":"Megaflis Sørlandsparken AS","ERPHostCompanyNo":2,"WarehouseNo":1,"mmoms":"22 327 704 kr","umoms":"17 862 163 kr","antord":" 17 074","prord":" 1 308 kr"},{"butikk":"Megaflis Tønsberg AS","ERPHostCompanyNo":3,"WarehouseNo":1,"mmoms":"24 325 974 kr","umoms":"19 460 779 kr","antord":" 20 437","prord":" 1 190 kr"},{"butikk":"Megaflis Agderparken AS","ERPHostCompanyNo":4,"WarehouseNo":1,"mmoms":"32 603 036 kr","umoms":"26 082 429 kr","antord":" 26 908","prord":" 1 212 kr"},{"butikk":"Megaflis Sandefjord AS","ERPHostCompanyNo":10,"WarehouseNo":1,"mmoms":"19 898 758 kr","umoms":"15 919 006 kr","antord":" 17 067","prord":" 1 166 kr"},{"butikk":"Megaflis Larvik AS","ERPHostCompanyNo":16,"WarehouseNo":1,"mmoms":"15 286 904 kr","umoms":"12 229 523 kr","antord":" 11 883","prord":" 1 286 kr"},{"butikk":"Totalt","ERPHostCompanyNo":9999,"WarehouseNo":9999,"mmoms":"152 778 662 kr","umoms":"122 222 930 kr","antord":" 122 781","prord":" 1 244 kr"}]
