[{"butikk":"Brødr. Berg Stenindustri AS avd. Skien","ERPHostCompanyNo":1,"WarehouseNo":1,"mmoms":"30 819 680 kr","umoms":"24 655 744 kr","antord":" 21 284","prord":" 1 448 kr"},{"butikk":"Brødr. Berg Stenindustri AS avd. Porsgrunn","ERPHostCompanyNo":1,"WarehouseNo":2,"mmoms":"5 222 458 kr","umoms":"4 177 966 kr","antord":" 6 321","prord":"  826 kr"},{"butikk":"Megaflis Sørlandsparken AS","ERPHostCompanyNo":2,"WarehouseNo":1,"mmoms":"21 124 908 kr","umoms":"16 899 927 kr","antord":" 16 120","prord":" 1 310 kr"},{"butikk":"Megaflis Tønsberg AS","ERPHostCompanyNo":3,"WarehouseNo":1,"mmoms":"22 818 397 kr","umoms":"18 254 718 kr","antord":" 19 131","prord":" 1 193 kr"},{"butikk":"Megaflis Agderparken AS","ERPHostCompanyNo":4,"WarehouseNo":1,"mmoms":"30 717 783 kr","umoms":"24 574 226 kr","antord":" 25 419","prord":" 1 208 kr"},{"butikk":"Megaflis Sandefjord AS","ERPHostCompanyNo":10,"WarehouseNo":1,"mmoms":"18 753 957 kr","umoms":"15 003 166 kr","antord":" 15 994","prord":" 1 173 kr"},{"butikk":"Megaflis Larvik AS","ERPHostCompanyNo":16,"WarehouseNo":1,"mmoms":"14 354 130 kr","umoms":"11 483 304 kr","antord":" 11 157","prord":" 1 287 kr"},{"butikk":"Totalt","ERPHostCompanyNo":9999,"WarehouseNo":9999,"mmoms":"143 811 313 kr","umoms":"115 049 050 kr","antord":" 115 426","prord":" 1 246 kr"}]
