[{"butikk":"Brødr. Berg Stenindustri AS avd. Skien","ERPHostCompanyNo":1,"WarehouseNo":1,"mmoms":"73 921 623 kr","umoms":"59 137 298 kr","antord":" 53 799","prord":" 1 374 kr"},{"butikk":"Brødr. Berg Stenindustri AS avd. Porsgrunn","ERPHostCompanyNo":1,"WarehouseNo":2,"mmoms":"13 362 381 kr","umoms":"10 689 905 kr","antord":" 16 452","prord":"  812 kr"},{"butikk":"Megaflis Sørlandsparken AS","ERPHostCompanyNo":2,"WarehouseNo":1,"mmoms":"48 963 725 kr","umoms":"39 170 980 kr","antord":" 38 514","prord":" 1 271 kr"},{"butikk":"Megaflis Tønsberg AS","ERPHostCompanyNo":3,"WarehouseNo":1,"mmoms":"55 855 788 kr","umoms":"44 684 631 kr","antord":" 48 573","prord":" 1 150 kr"},{"butikk":"Megaflis Agderparken AS","ERPHostCompanyNo":4,"WarehouseNo":1,"mmoms":"70 238 268 kr","umoms":"56 190 614 kr","antord":" 60 902","prord":" 1 153 kr"},{"butikk":"Megaflis Sandefjord AS","ERPHostCompanyNo":10,"WarehouseNo":1,"mmoms":"45 718 985 kr","umoms":"36 575 188 kr","antord":" 41 088","prord":" 1 113 kr"},{"butikk":"Megaflis Larvik AS","ERPHostCompanyNo":16,"WarehouseNo":1,"mmoms":"35 090 299 kr","umoms":"28 072 240 kr","antord":" 28 970","prord":" 1 211 kr"},{"butikk":"Totalt","ERPHostCompanyNo":9999,"WarehouseNo":9999,"mmoms":"343 151 069 kr","umoms":"274 520 855 kr","antord":" 288 298","prord":" 1 190 kr"}]
