[{"butikk":"Brødr. Berg Stenindustri AS avd. Skien","ERPHostCompanyNo":1,"WarehouseNo":1,"mmoms":" 56 150 kr","umoms":" 44 920 kr","db":" 15 547 kr","dg":"34.61%","antord":"  74","prord":"  759 kr"},{"butikk":"Brødr. Berg Stenindustri AS avd. Porsgrunn","ERPHostCompanyNo":1,"WarehouseNo":2,"mmoms":" 8 613 kr","umoms":" 6 890 kr","db":" 2 410 kr","dg":"34.98%","antord":"  21","prord":"  410 kr"},{"butikk":"Megaflis Sørlandsparken AS","ERPHostCompanyNo":2,"WarehouseNo":1,"mmoms":" 32 758 kr","umoms":" 26 206 kr","db":" 9 120 kr","dg":"34.80%","antord":"  35","prord":"  936 kr"},{"butikk":"Megaflis Tønsberg AS","ERPHostCompanyNo":3,"WarehouseNo":1,"mmoms":" 49 612 kr","umoms":" 39 689 kr","db":" 10 379 kr","dg":"26.15%","antord":"  73","prord":"  680 kr"},{"butikk":"Megaflis Agderparken AS","ERPHostCompanyNo":4,"WarehouseNo":1,"mmoms":" 54 392 kr","umoms":" 43 514 kr","db":" 14 913 kr","dg":"34.27%","antord":"  67","prord":"  812 kr"},{"butikk":"Megaflis Sandefjord AS","ERPHostCompanyNo":10,"WarehouseNo":1,"mmoms":" 69 569 kr","umoms":" 55 655 kr","db":" 15 908 kr","dg":"28.58%","antord":"  76","prord":"  915 kr"},{"butikk":"Megaflis Larvik AS","ERPHostCompanyNo":16,"WarehouseNo":1,"mmoms":" 34 968 kr","umoms":" 27 974 kr","db":" 11 271 kr","dg":"40.29%","antord":"  44","prord":"  795 kr"},{"butikk":"Totalt","ERPHostCompanyNo":9999,"WarehouseNo":9999,"mmoms":" 306 061 kr","umoms":" 244 849 kr","db":" 79 548 kr","dg":"32.49%","antord":"  390","prord":"  785 kr"}]
