[{"selger":"Fredrik Frost Pettersen","Beløp":" 11 603 kr","butikk":"Tønsberg"},{"selger":"Christopher Øglænd","Beløp":" 10 391 kr","butikk":"Kristiansand"},{"selger":"Sebastian Dahlen","Beløp":" 9 347 kr","butikk":"Arendal"},{"selger":"Ida Pernille Iversen","Beløp":" 6 206 kr","butikk":"BrBerg"},{"selger":"Menglei Chen Ottem","Beløp":" 5 890 kr","butikk":"Larvik"},{"selger":"Helen Rougnø","Beløp":" 5 782 kr","butikk":"Tønsberg"},{"selger":"Veronica Skaug Bolt Hansen","Beløp":" 5 240 kr","butikk":"Sandefjord"},{"selger":"Hans Kristian Nenset","Beløp":" 3 629 kr","butikk":"BrBerg"},{"selger":"Anders Eide","Beløp":" 2 939 kr","butikk":"Tønsberg"},{"selger":"Elin Eilefsen","Beløp":" 2 585 kr","butikk":"Larvik"}]
