[{"selger":"Maylin Trondahl Olsen","Beløp":" 55 953 kr","butikk":"Kristiansand"},{"selger":"Bertil Tangen","Beløp":" 46 351 kr","butikk":"Sandefjord"},{"selger":"Christopher Øglænd","Beløp":" 38 885 kr","butikk":"Kristiansand"},{"selger":"Sebastian Eppeland Hansen","Beløp":" 35 376 kr","butikk":"Arendal"},{"selger":"Håkon Tvede","Beløp":" 31 040 kr","butikk":"Arendal"},{"selger":"Iselin Sofie Skogland","Beløp":" 24 124 kr","butikk":"Tønsberg"},{"selger":"Pål Magnus Andersen","Beløp":" 24 061 kr","butikk":"Sandefjord"},{"selger":"Ida Pernille Iversen","Beløp":" 23 631 kr","butikk":"BrBerg"},{"selger":"Leah McGurty","Beløp":" 19 789 kr","butikk":"BrBerg"},{"selger":"Valeria Salinas","Beløp":" 18 878 kr","butikk":"Kristiansand"}]
