[{"selger":"Preben Jacobsen","Beløp":" 84 024 kr","butikk":"Arendal"},{"selger":"Joakim Johnsen","Beløp":" 52 186 kr","butikk":"BrBerg"},{"selger":"Fredrik Frost Pettersen","Beløp":" 43 491 kr","butikk":"Tønsberg"},{"selger":"Jonas Garstad","Beløp":" 38 829 kr","butikk":"BrBerg"},{"selger":"Bertil Tangen","Beløp":" 35 763 kr","butikk":"Sandefjord"},{"selger":"Ida Pernille Iversen","Beløp":" 35 063 kr","butikk":"BrBerg"},{"selger":"Aleksander Bang","Beløp":" 33 930 kr","butikk":"BrBerg"},{"selger":"Veronica Skaug Bolt Hansen","Beløp":" 33 452 kr","butikk":"Sandefjord"},{"selger":"Lina BergHoltz","Beløp":" 32 407 kr","butikk":"Larvik"},{"selger":"Menglei Chen Ottem","Beløp":" 30 147 kr","butikk":"Larvik"}]
