[{"selger":"Valeria Salinas","Beløp":" 88 577 kr","butikk":"Kristiansand"},{"selger":"Nadia Tveit Ramse","Beløp":" 71 521 kr","butikk":"Arendal"},{"selger":"Christopher Øglænd","Beløp":" 64 609 kr","butikk":"Kristiansand"},{"selger":"Kristine Martinsen","Beløp":" 62 952 kr","butikk":"Arendal"},{"selger":"Erica Hegge Nilsen","Beløp":" 62 541 kr","butikk":"Sandefjord"},{"selger":"Fredrik Frost Pettersen","Beløp":" 59 430 kr","butikk":"Tønsberg"},{"selger":"Anniken Semb Kvalsund","Beløp":" 44 312 kr","butikk":"Larvik"},{"selger":"Fredrik Mølmen","Beløp":" 43 515 kr","butikk":"BrBerg"},{"selger":"Aleksander Bang","Beløp":" 41 058 kr","butikk":"BrBerg"},{"selger":"Linn Kristine Terjesen","Beløp":" 39 867 kr","butikk":"Arendal"}]
