[{"selger":"Fredrik Frost Pettersen","Beløp":" 85 092 kr","butikk":"Tønsberg"},{"selger":"Helena Frederikke Strand","Beløp":" 61 524 kr","butikk":"Tønsberg"},{"selger":"Linn Kristine Terjesen","Beløp":" 44 431 kr","butikk":"Arendal"},{"selger":"Preben Jacobsen","Beløp":" 43 351 kr","butikk":"Arendal"},{"selger":"Elin Eilefsen","Beløp":" 39 646 kr","butikk":"Larvik"},{"selger":"Laila Skripeland","Beløp":" 37 411 kr","butikk":"Arendal"},{"selger":"Pål Magnus Andersen","Beløp":" 37 087 kr","butikk":"Sandefjord"},{"selger":"Jelle Soest","Beløp":" 36 775 kr","butikk":"Kristiansand"},{"selger":"Aslak Ludvigsen","Beløp":" 35 414 kr","butikk":"Arendal"},{"selger":"Helen Rougnø","Beløp":" 34 874 kr","butikk":"Tønsberg"}]
