[{"butikk":"Brødr. Berg Stenindustri AS avd. Skien","ERPHostCompanyNo":1,"WarehouseNo":1,"mmoms":" 243 362 kr","umoms":" 194 690 kr","db":" 48 922 kr","dg":"25.13%","antord":"  168","prord":" 1 449 kr"},{"butikk":"Brødr. Berg Stenindustri AS avd. Porsgrunn","ERPHostCompanyNo":1,"WarehouseNo":2,"mmoms":" 59 417 kr","umoms":" 47 534 kr","db":" 10 461 kr","dg":"22.01%","antord":"  49","prord":" 1 213 kr"},{"butikk":"Megaflis Sørlandsparken AS","ERPHostCompanyNo":2,"WarehouseNo":1,"mmoms":" 108 349 kr","umoms":" 86 679 kr","db":" 27 327 kr","dg":"31.53%","antord":"  106","prord":" 1 022 kr"},{"butikk":"Megaflis Tønsberg AS","ERPHostCompanyNo":3,"WarehouseNo":1,"mmoms":" 198 913 kr","umoms":" 159 131 kr","db":" 48 319 kr","dg":"30.36%","antord":"  173","prord":" 1 150 kr"},{"butikk":"Megaflis Agderparken AS","ERPHostCompanyNo":4,"WarehouseNo":1,"mmoms":" 193 846 kr","umoms":" 155 077 kr","db":" 37 160 kr","dg":"23.96%","antord":"  176","prord":" 1 101 kr"},{"butikk":"Megaflis Sandefjord AS","ERPHostCompanyNo":10,"WarehouseNo":1,"mmoms":" 153 321 kr","umoms":" 122 657 kr","db":" 29 802 kr","dg":"24.30%","antord":"  133","prord":" 1 153 kr"},{"butikk":"Megaflis Larvik AS","ERPHostCompanyNo":16,"WarehouseNo":1,"mmoms":" 96 344 kr","umoms":" 77 075 kr","db":" 21 938 kr","dg":"28.46%","antord":"  117","prord":"  823 kr"},{"butikk":"Totalt","ERPHostCompanyNo":9999,"WarehouseNo":9999,"mmoms":"1 053 554 kr","umoms":" 842 843 kr","db":" 223 929 kr","dg":"26.57%","antord":"  922","prord":" 1 143 kr"}]
