[{"butikk":"Skien","Klient":0,"mmoms":" 371 889 kr","umoms":" 297 511 kr","db":" 38 343 kr","dg":"12.9%","antord":"  225","prord":" 1 653 kr"},{"butikk":"Porsgrunn","Klient":1,"mmoms":" 28 587 kr","umoms":" 22 869 kr","db":" 4 864 kr","dg":"21.3%","antord":"  56","prord":"  510 kr"},{"butikk":"Kristiansand","Klient":2,"mmoms":" 167 052 kr","umoms":" 133 642 kr","db":" 20 476 kr","dg":"15.3%","antord":"  132","prord":" 1 266 kr"},{"butikk":"Tønsberg","Klient":3,"mmoms":" 271 597 kr","umoms":" 217 278 kr","db":" 33 945 kr","dg":"15.6%","antord":"  239","prord":" 1 136 kr"},{"butikk":"Arendal","Klient":4,"mmoms":" 172 608 kr","umoms":" 138 086 kr","db":" 38 939 kr","dg":"28.2%","antord":"  222","prord":"  778 kr"},{"butikk":"Sandefjord","Klient":5,"mmoms":" 195 172 kr","umoms":" 156 138 kr","db":" 33 903 kr","dg":"21.7%","antord":"  191","prord":" 1 022 kr"},{"butikk":"Larvik","Klient":6,"mmoms":" 103 782 kr","umoms":" 83 025 kr","db":" 21 422 kr","dg":"25.8%","antord":"  141","prord":"  736 kr"},{"butikk":"Totalt","Klient":9999,"mmoms":"1 310 686 kr","umoms":"1 048 549 kr","db":" 191 891 kr","dg":"18.3%","antord":" 1 206","prord":" 1 087 kr"}]
