[{"butikk":"Brødr. Berg Stenindustri AS avd. Skien","ERPHostCompanyNo":1,"WarehouseNo":1,"mmoms":" 93 581 kr","umoms":" 74 865 kr","antord":"  69","prord":" 1 356 kr"},{"butikk":"Brødr. Berg Stenindustri AS avd. Porsgrunn","ERPHostCompanyNo":1,"WarehouseNo":2,"mmoms":" 38 917 kr","umoms":" 31 134 kr","antord":"  26","prord":" 1 497 kr"},{"butikk":"Megaflis Sørlandsparken AS","ERPHostCompanyNo":2,"WarehouseNo":1,"mmoms":" 99 157 kr","umoms":" 79 326 kr","antord":"  53","prord":" 1 871 kr"},{"butikk":"Megaflis Tønsberg AS","ERPHostCompanyNo":3,"WarehouseNo":1,"mmoms":" 64 485 kr","umoms":" 51 588 kr","antord":"  81","prord":"  796 kr"},{"butikk":"Megaflis Agderparken AS","ERPHostCompanyNo":4,"WarehouseNo":1,"mmoms":" 92 973 kr","umoms":" 74 378 kr","antord":"  86","prord":" 1 081 kr"},{"butikk":"Megaflis Sandefjord AS","ERPHostCompanyNo":10,"WarehouseNo":1,"mmoms":" 79 125 kr","umoms":" 63 300 kr","antord":"  78","prord":" 1 014 kr"},{"butikk":"Megaflis Larvik AS","ERPHostCompanyNo":16,"WarehouseNo":1,"mmoms":" 66 475 kr","umoms":" 53 180 kr","antord":"  36","prord":" 1 847 kr"},{"butikk":"Totalt","ERPHostCompanyNo":9999,"WarehouseNo":9999,"mmoms":" 534 714 kr","umoms":" 427 771 kr","antord":"  429","prord":" 1 246 kr"}]
