[{"selger":"Heidi Kihle Lindvig","Beløp":" 13 592 kr","butikk":"BrBerg"},{"selger":"Netthandel","Beløp":" 6 390 kr","butikk":"Larvik"},{"selger":"James Michael McGurty","Beløp":" 5 272 kr","butikk":"BrBerg"},{"selger":"Ståle Skjævestad","Beløp":" 1 314 kr","butikk":"Kristiansand"},{"selger":"Maylin Trondahl Olsen","Beløp":"  958 kr","butikk":"Kristiansand"},{"selger":"Håkon Tvede","Beløp":"  763 kr","butikk":"Arendal"},{"selger":"Helen Rougnø","Beløp":"  716 kr","butikk":"Tønsberg"},{"selger":"Elin Eilefsen","Beløp":"  218 kr","butikk":"Larvik"},{"selger":"Fredrik Frost Pettersen","Beløp":"  199 kr","butikk":"Tønsberg"},{"selger":"Veronica Skaug Bolt Hansen","Beløp":"  146 kr","butikk":"Sandefjord"}]
