[{"selger":"Laila Skripeland","Beløp":" 58 447 kr","butikk":"Arendal"},{"selger":"Leah McGurty","Beløp":" 50 407 kr","butikk":"BrBerg"},{"selger":"Fredrik Frost Pettersen","Beløp":" 43 138 kr","butikk":"Tønsberg"},{"selger":"Bertil Tangen","Beløp":" 36 798 kr","butikk":"Sandefjord"},{"selger":"Rikke Rosseli","Beløp":" 34 492 kr","butikk":"Kristiansand"},{"selger":"Ida Serine Skogland","Beløp":" 32 486 kr","butikk":"Tønsberg"},{"selger":"Joakim Johnsen","Beløp":" 31 947 kr","butikk":"BrBerg"},{"selger":"Maylin Trondahl Olsen","Beløp":" 28 991 kr","butikk":"Kristiansand"},{"selger":"Kristine Lovise Odland","Beløp":" 25 246 kr","butikk":"Arendal"},{"selger":"Sjur A","Beløp":" 24 543 kr","butikk":"Arendal"}]
