[{"butikk":"Brødr. Berg Stenindustri AS avd. Skien","ERPHostCompanyNo":1,"WarehouseNo":1,"mmoms":" 192 230 kr","umoms":" 153 784 kr","db":" 36 809 kr","dg":"23.94%","antord":"  146","prord":" 1 317 kr"},{"butikk":"Brødr. Berg Stenindustri AS avd. Porsgrunn","ERPHostCompanyNo":1,"WarehouseNo":2,"mmoms":" 40 940 kr","umoms":" 32 752 kr","db":" 11 385 kr","dg":"34.76%","antord":"  48","prord":"  853 kr"},{"butikk":"Megaflis Sørlandsparken AS","ERPHostCompanyNo":2,"WarehouseNo":1,"mmoms":" 90 381 kr","umoms":" 72 305 kr","db":" 21 264 kr","dg":"29.41%","antord":"  107","prord":"  845 kr"},{"butikk":"Megaflis Tønsberg AS","ERPHostCompanyNo":3,"WarehouseNo":1,"mmoms":" 196 578 kr","umoms":" 157 262 kr","db":" 39 519 kr","dg":"25.13%","antord":"  139","prord":" 1 414 kr"},{"butikk":"Megaflis Agderparken AS","ERPHostCompanyNo":4,"WarehouseNo":1,"mmoms":" 187 408 kr","umoms":" 149 927 kr","db":" 45 516 kr","dg":"30.36%","antord":"  162","prord":" 1 157 kr"},{"butikk":"Megaflis Sandefjord AS","ERPHostCompanyNo":10,"WarehouseNo":1,"mmoms":" 144 176 kr","umoms":" 115 341 kr","db":" 36 220 kr","dg":"31.40%","antord":"  122","prord":" 1 182 kr"},{"butikk":"Megaflis Larvik AS","ERPHostCompanyNo":16,"WarehouseNo":1,"mmoms":" 103 591 kr","umoms":" 82 873 kr","db":" 19 576 kr","dg":"23.62%","antord":"  78","prord":" 1 328 kr"},{"butikk":"Totalt","ERPHostCompanyNo":9999,"WarehouseNo":9999,"mmoms":" 955 303 kr","umoms":" 764 243 kr","db":" 210 290 kr","dg":"27.52%","antord":"  802","prord":" 1 191 kr"}]
