[{"selger":"Silje Hansen Røed","Beløp":" 46 351 kr","butikk":"Sandefjord"},{"selger":"Fredrik Mølmen","Beløp":" 43 409 kr","butikk":"BrBerg"},{"selger":"Fredrik Orvedal","Beløp":" 30 036 kr","butikk":"Tønsberg"},{"selger":"Laila Skripeland","Beløp":" 27 907 kr","butikk":"Arendal"},{"selger":"Pål Magnus Andersen","Beløp":" 27 379 kr","butikk":"Sandefjord"},{"selger":"Christoffer Fosstvedt","Beløp":" 26 974 kr","butikk":"BrBerg"},{"selger":"Preben Jacobsen","Beløp":" 24 155 kr","butikk":"Arendal"},{"selger":"Elias Findal","Beløp":" 23 997 kr","butikk":"BrBerg"},{"selger":"Hans Kristian Nenset","Beløp":" 23 699 kr","butikk":"BrBerg"},{"selger":"Jonas Garstad","Beløp":" 23 157 kr","butikk":"BrBerg"}]
