[{"butikk":"Brødr. Berg Stenindustri AS avd. Skien","ERPHostCompanyNo":1,"WarehouseNo":1,"mmoms":" 197 367 kr","umoms":" 157 894 kr","db":" 30 415 kr","dg":"19.26%","antord":"  139","prord":" 1 420 kr"},{"butikk":"Brødr. Berg Stenindustri AS avd. Porsgrunn","ERPHostCompanyNo":1,"WarehouseNo":2,"mmoms":" 59 902 kr","umoms":" 47 921 kr","db":" 13 169 kr","dg":"27.48%","antord":"  54","prord":" 1 109 kr"},{"butikk":"Megaflis Sørlandsparken AS","ERPHostCompanyNo":2,"WarehouseNo":1,"mmoms":" 69 451 kr","umoms":" 55 561 kr","db":" 16 803 kr","dg":"30.24%","antord":"  90","prord":"  772 kr"},{"butikk":"Megaflis Tønsberg AS","ERPHostCompanyNo":3,"WarehouseNo":1,"mmoms":" 249 977 kr","umoms":" 199 982 kr","db":" 39 283 kr","dg":"19.64%","antord":"  173","prord":" 1 445 kr"},{"butikk":"Megaflis Agderparken AS","ERPHostCompanyNo":4,"WarehouseNo":1,"mmoms":" 206 526 kr","umoms":" 165 221 kr","db":" 48 509 kr","dg":"29.36%","antord":"  143","prord":" 1 444 kr"},{"butikk":"Megaflis Sandefjord AS","ERPHostCompanyNo":10,"WarehouseNo":1,"mmoms":" 164 670 kr","umoms":" 131 736 kr","db":" 32 349 kr","dg":"24.56%","antord":"  119","prord":" 1 384 kr"},{"butikk":"Megaflis Larvik AS","ERPHostCompanyNo":16,"WarehouseNo":1,"mmoms":" 74 770 kr","umoms":" 59 816 kr","db":" 9 232 kr","dg":"15.43%","antord":"  79","prord":"  946 kr"},{"butikk":"Totalt","ERPHostCompanyNo":9999,"WarehouseNo":9999,"mmoms":"1 022 663 kr","umoms":" 818 131 kr","db":" 189 760 kr","dg":"23.19%","antord":"  797","prord":" 1 283 kr"}]
