[{"selger":"Aleksander Bang","Beløp":" 58 188 kr","butikk":"BrBerg"},{"selger":"Preben Jacobsen","Beløp":" 43 419 kr","butikk":"Arendal"},{"selger":"Heidi Kihle Lindvig","Beløp":" 37 477 kr","butikk":"BrBerg"},{"selger":"Knut Rasmussen","Beløp":" 32 187 kr","butikk":"Kristiansand"},{"selger":"Iselin Sofie Skogland","Beløp":" 30 581 kr","butikk":"Tønsberg"},{"selger":"Alexander Fevang","Beløp":" 28 665 kr","butikk":"Tønsberg"},{"selger":"Alexander Firing Hansen","Beløp":" 18 215 kr","butikk":"Tønsberg"},{"selger":"Pål Magnus Andersen","Beløp":" 17 635 kr","butikk":"Sandefjord"},{"selger":"Ståle Skjævestad","Beløp":" 16 101 kr","butikk":"Kristiansand"},{"selger":"Dennis Haugen Warelius","Beløp":" 13 888 kr","butikk":"Tønsberg"}]
