[{"butikk":"Skien","Klient":0,"mmoms":"2 030 747 kr","umoms":"1 624 598 kr","db":" 367 475 kr","dg":"22.6%","antord":" 1 246","prord":" 1 630 kr"},{"butikk":"Porsgrunn","Klient":1,"mmoms":" 179 134 kr","umoms":" 143 307 kr","db":" 33 132 kr","dg":"23.1%","antord":"  316","prord":"  567 kr"},{"butikk":"Kristiansand","Klient":2,"mmoms":"1 222 727 kr","umoms":" 978 181 kr","db":" 212 394 kr","dg":"21.7%","antord":"  913","prord":" 1 339 kr"},{"butikk":"Tønsberg","Klient":3,"mmoms":"1 492 347 kr","umoms":"1 193 878 kr","db":" 278 625 kr","dg":"23.3%","antord":" 1 267","prord":" 1 178 kr"},{"butikk":"Arendal","Klient":4,"mmoms":"1 583 548 kr","umoms":"1 266 838 kr","db":" 306 330 kr","dg":"24.2%","antord":" 1 327","prord":" 1 193 kr"},{"butikk":"Sandefjord","Klient":5,"mmoms":"1 111 145 kr","umoms":" 888 916 kr","db":" 217 119 kr","dg":"24.4%","antord":"  990","prord":" 1 122 kr"},{"butikk":"Larvik","Klient":6,"mmoms":" 773 639 kr","umoms":" 618 911 kr","db":" 151 866 kr","dg":"24.5%","antord":"  704","prord":" 1 099 kr"},{"butikk":"Totalt","Klient":9999,"mmoms":"8 393 286 kr","umoms":"6 714 629 kr","db":"1 566 940 kr","dg":"23.3%","antord":" 6 763","prord":" 1 241 kr"}]
