[{"butikk":"Brødr. Berg Stenindustri AS avd. Skien","ERPHostCompanyNo":1,"WarehouseNo":1,"mmoms":"4 693 631 kr","umoms":"3 754 905 kr","db":" 949 298 kr","dg":"25.28%","antord":" 3 608","prord":" 1 301 kr"},{"butikk":"Brødr. Berg Stenindustri AS avd. Porsgrunn","ERPHostCompanyNo":1,"WarehouseNo":2,"mmoms":" 967 904 kr","umoms":" 774 323 kr","db":" 176 478 kr","dg":"22.79%","antord":" 1 105","prord":"  876 kr"},{"butikk":"Megaflis Sørlandsparken AS","ERPHostCompanyNo":2,"WarehouseNo":1,"mmoms":"2 670 233 kr","umoms":"2 136 186 kr","db":" 566 408 kr","dg":"26.51%","antord":" 2 235","prord":" 1 195 kr"},{"butikk":"Megaflis Tønsberg AS","ERPHostCompanyNo":3,"WarehouseNo":1,"mmoms":"3 970 493 kr","umoms":"3 176 394 kr","db":" 871 758 kr","dg":"27.44%","antord":" 3 543","prord":" 1 121 kr"},{"butikk":"Megaflis Agderparken AS","ERPHostCompanyNo":4,"WarehouseNo":1,"mmoms":"3 838 916 kr","umoms":"3 071 133 kr","db":" 791 206 kr","dg":"25.76%","antord":" 3 551","prord":" 1 081 kr"},{"butikk":"Megaflis Sandefjord AS","ERPHostCompanyNo":10,"WarehouseNo":1,"mmoms":"2 880 529 kr","umoms":"2 304 424 kr","db":" 628 086 kr","dg":"27.26%","antord":" 2 650","prord":" 1 087 kr"},{"butikk":"Megaflis Larvik AS","ERPHostCompanyNo":16,"WarehouseNo":1,"mmoms":"2 248 485 kr","umoms":"1 798 788 kr","db":" 468 588 kr","dg":"26.05%","antord":" 1 938","prord":" 1 160 kr"},{"butikk":"Totalt","ERPHostCompanyNo":9999,"WarehouseNo":9999,"mmoms":"21 270 191 kr","umoms":"17 016 153 kr","db":"4 451 822 kr","dg":"26.16%","antord":" 18 630","prord":" 1 142 kr"}]
