[{"butikk":"Brødr. Berg Stenindustri AS avd. Skien","mmoms":" 637 647 kr","umoms":" 510 118 kr","db":" 174 118 kr","dg":"1.99%","antord":" 1 171","prord":"-  192 kr"},{"butikk":"Brødr. Berg Stenindustri AS avd. Porsgrunn","mmoms":" 80 078 kr","umoms":" 64 063 kr","db":" 49 601 kr","dg":"6.63%","antord":"  306","prord":"-  183 kr"},{"butikk":"Megaflis Sørlandsparken AS","mmoms":" 461 688 kr","umoms":" 369 350 kr","db":" 133 547 kr","dg":"2.39%","antord":"  601","prord":"-  68 kr"},{"butikk":"Megaflis Tønsberg AS","mmoms":" 588 072 kr","umoms":" 470 458 kr","db":" 202 427 kr","dg":"3.75%","antord":"  842","prord":"-  51 kr"},{"butikk":"Megaflis Agderparken AS","mmoms":"1 037 186 kr","umoms":" 829 749 kr","db":" 250 914 kr","dg":"1.66%","antord":" 1 154","prord":"-  7 kr"},{"butikk":"Megaflis Sandefjord AS","mmoms":" 693 567 kr","umoms":" 554 854 kr","db":" 182 752 kr","dg":"1.66%","antord":"  903","prord":"-  22 kr"},{"butikk":"Megaflis Larvik AS","mmoms":" 860 038 kr","umoms":" 688 030 kr","db":" 153 008 kr","dg":"-3.17%","antord":"  764","prord":"  103 kr"},{"butikk":"Totalt","mmoms":"4 150 891 kr","umoms":"3 320 713 kr","db":"1 089 705 kr","dg":"1.89%","antord":" 5 640","prord":"-  67 kr"}]
