[{"butikk":"Brødr. Berg Stenindustri AS avd. Skien","mmoms":" 327 384 kr","umoms":" 261 907 kr","db":" 119 552 kr","dg":"4.25%","antord":"  618","prord":"-  172 kr"},{"butikk":"Brødr. Berg Stenindustri AS avd. Porsgrunn","mmoms":" 38 647 kr","umoms":" 30 918 kr","db":" 22 184 kr","dg":"4.99%","antord":"  153","prord":"-  150 kr"},{"butikk":"Megaflis Sørlandsparken AS","mmoms":" 289 120 kr","umoms":" 231 296 kr","db":" 83 598 kr","dg":"2.55%","antord":"  286","prord":"  9 kr"},{"butikk":"Megaflis Tønsberg AS","mmoms":" 225 673 kr","umoms":" 180 538 kr","db":" 94 624 kr","dg":"3.98%","antord":"  385","prord":"-  63 kr"},{"butikk":"Megaflis Agderparken AS","mmoms":" 562 805 kr","umoms":" 450 244 kr","db":" 137 347 kr","dg":"1.69%","antord":"  554","prord":"  46 kr"},{"butikk":"Megaflis Sandefjord AS","mmoms":" 217 745 kr","umoms":" 174 196 kr","db":" 66 732 kr","dg":"2.05%","antord":"  399","prord":"-  85 kr"},{"butikk":"Megaflis Larvik AS","mmoms":" 552 563 kr","umoms":" 442 050 kr","db":" 100 562 kr","dg":"-3.10%","antord":"  364","prord":"  246 kr"},{"butikk":"Totalt","mmoms":"2 006 550 kr","umoms":"1 605 240 kr","db":" 567 937 kr","dg":"2.22%","antord":" 2 658","prord":"-  45 kr"}]
