[{"butikk":"Brødr. Berg Stenindustri AS avd. Skien","ERPHostCompanyNo":1,"WarehouseNo":1,"mmoms":" 42 703 kr","umoms":" 34 162 kr","antord":"  58","prord":"  736 kr"},{"butikk":"Brødr. Berg Stenindustri AS avd. Porsgrunn","ERPHostCompanyNo":1,"WarehouseNo":2,"mmoms":" 8 293 kr","umoms":" 6 635 kr","antord":"  14","prord":"  592 kr"},{"butikk":"Megaflis Sørlandsparken AS","ERPHostCompanyNo":2,"WarehouseNo":1,"mmoms":" 29 888 kr","umoms":" 23 910 kr","antord":"  33","prord":"  906 kr"},{"butikk":"Megaflis Tønsberg AS","ERPHostCompanyNo":3,"WarehouseNo":1,"mmoms":" 55 772 kr","umoms":" 44 617 kr","antord":"  59","prord":"  945 kr"},{"butikk":"Megaflis Agderparken AS","ERPHostCompanyNo":4,"WarehouseNo":1,"mmoms":" 49 132 kr","umoms":" 39 306 kr","antord":"  65","prord":"  756 kr"},{"butikk":"Megaflis Sandefjord AS","ERPHostCompanyNo":10,"WarehouseNo":1,"mmoms":" 117 958 kr","umoms":" 94 367 kr","antord":"  53","prord":" 2 226 kr"},{"butikk":"Megaflis Larvik AS","ERPHostCompanyNo":16,"WarehouseNo":1,"mmoms":" 19 236 kr","umoms":" 15 389 kr","antord":"  26","prord":"  740 kr"},{"butikk":"Totalt","ERPHostCompanyNo":9999,"WarehouseNo":9999,"mmoms":" 322 982 kr","umoms":" 258 386 kr","antord":"  308","prord":" 1 049 kr"}]
