[{"butikk":"Brødr. Berg Stenindustri AS avd. Skien","ERPHostCompanyNo":1,"WarehouseNo":1,"mmoms":"5 138 460 kr","umoms":"4 110 768 kr","antord":" 3 579","prord":" 1 436 kr"},{"butikk":"Brødr. Berg Stenindustri AS avd. Porsgrunn","ERPHostCompanyNo":1,"WarehouseNo":2,"mmoms":" 748 378 kr","umoms":" 598 702 kr","antord":"  984","prord":"  761 kr"},{"butikk":"Megaflis Sørlandsparken AS","ERPHostCompanyNo":2,"WarehouseNo":1,"mmoms":"2 552 311 kr","umoms":"2 041 849 kr","antord":" 2 100","prord":" 1 215 kr"},{"butikk":"Megaflis Tønsberg AS","ERPHostCompanyNo":3,"WarehouseNo":1,"mmoms":"3 792 841 kr","umoms":"3 034 273 kr","antord":" 3 063","prord":" 1 238 kr"},{"butikk":"Megaflis Agderparken AS","ERPHostCompanyNo":4,"WarehouseNo":1,"mmoms":"4 132 141 kr","umoms":"3 305 713 kr","antord":" 3 527","prord":" 1 172 kr"},{"butikk":"Megaflis Sandefjord AS","ERPHostCompanyNo":10,"WarehouseNo":1,"mmoms":"2 614 197 kr","umoms":"2 091 357 kr","antord":" 2 461","prord":" 1 062 kr"},{"butikk":"Megaflis Larvik AS","ERPHostCompanyNo":16,"WarehouseNo":1,"mmoms":"2 240 309 kr","umoms":"1 792 248 kr","antord":" 1 776","prord":" 1 261 kr"},{"butikk":"Totalt","ERPHostCompanyNo":9999,"WarehouseNo":9999,"mmoms":"21 218 952 kr","umoms":"16 975 162 kr","antord":" 17 491","prord":" 1 213 kr"}]
