[{"butikk":"Brødr. Berg Stenindustri AS avd. Skien","ERPHostCompanyNo":1,"WarehouseNo":1,"mmoms":"7 356 275 kr","umoms":"5 885 020 kr","antord":" 5 430","prord":" 1 355 kr"},{"butikk":"Brødr. Berg Stenindustri AS avd. Porsgrunn","ERPHostCompanyNo":1,"WarehouseNo":2,"mmoms":"1 298 465 kr","umoms":"1 038 772 kr","antord":" 1 673","prord":"  776 kr"},{"butikk":"Megaflis Sørlandsparken AS","ERPHostCompanyNo":2,"WarehouseNo":1,"mmoms":"5 026 645 kr","umoms":"4 021 316 kr","antord":" 4 044","prord":" 1 243 kr"},{"butikk":"Megaflis Tønsberg AS","ERPHostCompanyNo":3,"WarehouseNo":1,"mmoms":"5 907 550 kr","umoms":"4 726 040 kr","antord":" 5 205","prord":" 1 135 kr"},{"butikk":"Megaflis Agderparken AS","ERPHostCompanyNo":4,"WarehouseNo":1,"mmoms":"7 346 845 kr","umoms":"5 877 476 kr","antord":" 6 567","prord":" 1 119 kr"},{"butikk":"Megaflis Sandefjord AS","ERPHostCompanyNo":10,"WarehouseNo":1,"mmoms":"4 664 480 kr","umoms":"3 731 584 kr","antord":" 4 186","prord":" 1 114 kr"},{"butikk":"Megaflis Larvik AS","ERPHostCompanyNo":16,"WarehouseNo":1,"mmoms":"3 341 175 kr","umoms":"2 672 940 kr","antord":" 2 773","prord":" 1 205 kr"},{"butikk":"Totalt","ERPHostCompanyNo":9999,"WarehouseNo":9999,"mmoms":"34 945 434 kr","umoms":"27 956 348 kr","antord":" 29 879","prord":" 1 170 kr"}]
