[{"butikk":"Skien","mmoms":"- 26 963 kr","umoms":"- 21 570 kr","db":" 8 030 kr","dg":"1.4%","antord":"-  88","prord":"  88 kr"},{"butikk":"Kristiansand","mmoms":"- 92 515 kr","umoms":"- 74 012 kr","db":"- 29 436 kr","dg":"-2.0%","antord":"  58","prord":"-  306 kr"},{"butikk":"Tønsberg","mmoms":"- 186 582 kr","umoms":"- 149 266 kr","db":"- 9 469 kr","dg":"3.7%","antord":"-  130","prord":"-  55 kr"},{"butikk":"Arendal","mmoms":"- 243 372 kr","umoms":"- 194 698 kr","db":"- 60 194 kr","dg":"-1.6%","antord":"-  20","prord":"-  229 kr"},{"butikk":"Sandefjord","mmoms":"- 100 923 kr","umoms":"- 80 739 kr","db":"- 11 244 kr","dg":"1.7%","antord":"  0","prord":"-  161 kr"},{"butikk":"Larvik","mmoms":"- 179 057 kr","umoms":"- 143 245 kr","db":"- 29 185 kr","dg":"1.2%","antord":"-  44","prord":"-  292 kr"},{"butikk":"Totalt","mmoms":"- 950 701 kr","umoms":"- 760 561 kr","db":"- 156 069 kr","dg":"0.6%","antord":"-  438","prord":"-  102 kr"}]
