[{"butikk":"Brødr. Berg Stenindustri AS avd. Skien","mmoms":"- 613 130 kr","umoms":"- 490 504 kr","antord":"-  504","prord":"  48 kr"},{"butikk":"Brødr. Berg Stenindustri AS avd. Porsgrunn","mmoms":"- 584 267 kr","umoms":"- 467 413 kr","antord":"-  432","prord":"-  316 kr"},{"butikk":"Megaflis Sørlandsparken AS","mmoms":"- 427 760 kr","umoms":"- 342 208 kr","antord":"-  137","prord":"-  170 kr"},{"butikk":"Megaflis Tønsberg AS","mmoms":"-1 158 064 kr","umoms":"- 926 451 kr","antord":"- 1 042","prord":"  30 kr"},{"butikk":"Megaflis Agderparken AS","mmoms":"- 135 830 kr","umoms":"- 108 664 kr","antord":"-  11","prord":"-  52 kr"},{"butikk":"Megaflis Sandefjord AS","mmoms":"-1 066 254 kr","umoms":"- 853 003 kr","antord":"-  682","prord":"-  182 kr"},{"butikk":"Megaflis Larvik AS","mmoms":"- 591 324 kr","umoms":"- 473 059 kr","antord":"-  380","prord":"-  130 kr"},{"butikk":"Totalt","mmoms":"-4 576 628 kr","umoms":"-3 661 303 kr","antord":"- 3 188","prord":"-  60 kr"}]
