[{"butikk":"Brødr. Berg Stenindustri AS avd. Skien","ERPHostCompanyNo":1,"WarehouseNo":1,"mmoms":" 822 229 kr","umoms":" 657 783 kr","antord":"  596","prord":" 1 380 kr"},{"butikk":"Brødr. Berg Stenindustri AS avd. Porsgrunn","ERPHostCompanyNo":1,"WarehouseNo":2,"mmoms":" 134 665 kr","umoms":" 107 732 kr","antord":"  190","prord":"  709 kr"},{"butikk":"Megaflis Sørlandsparken AS","ERPHostCompanyNo":2,"WarehouseNo":1,"mmoms":" 587 856 kr","umoms":" 470 285 kr","antord":"  468","prord":" 1 256 kr"},{"butikk":"Megaflis Tønsberg AS","ERPHostCompanyNo":3,"WarehouseNo":1,"mmoms":" 707 406 kr","umoms":" 565 925 kr","antord":"  587","prord":" 1 205 kr"},{"butikk":"Megaflis Agderparken AS","ERPHostCompanyNo":4,"WarehouseNo":1,"mmoms":" 800 449 kr","umoms":" 640 359 kr","antord":"  679","prord":" 1 179 kr"},{"butikk":"Megaflis Sandefjord AS","ERPHostCompanyNo":10,"WarehouseNo":1,"mmoms":" 519 626 kr","umoms":" 415 700 kr","antord":"  538","prord":"  966 kr"},{"butikk":"Megaflis Larvik AS","ERPHostCompanyNo":16,"WarehouseNo":1,"mmoms":" 492 894 kr","umoms":" 394 315 kr","antord":"  363","prord":" 1 358 kr"},{"butikk":"Totalt","ERPHostCompanyNo":9999,"WarehouseNo":9999,"mmoms":"4 065 123 kr","umoms":"3 252 099 kr","antord":" 3 421","prord":" 1 188 kr"}]
