[{"butikk":"Skien","mmoms":"-15 621 301 kr","umoms":"-12 497 041 kr","db":"-3 017 555 kr","dg":"-1.8%","antord":"- 10 828","prord":"  22 kr"},{"butikk":"Porsgrunn","mmoms":"-2 729 079 kr","umoms":"-2 183 263 kr","db":"- 499 149 kr","dg":"-2.2%","antord":"- 3 192","prord":"-  112 kr"},{"butikk":"Kristiansand","mmoms":"-10 736 420 kr","umoms":"-8 589 136 kr","db":"-2 211 304 kr","dg":"-2.4%","antord":"- 7 698","prord":"-  89 kr"},{"butikk":"Tønsberg","mmoms":"-10 902 419 kr","umoms":"-8 721 936 kr","db":"-2 260 755 kr","dg":"-3.5%","antord":"- 9 592","prord":"  142 kr"},{"butikk":"Arendal","mmoms":"-15 489 735 kr","umoms":"-12 391 788 kr","db":"-3 172 633 kr","dg":"-0.3%","antord":"- 12 066","prord":"-  82 kr"},{"butikk":"Sandefjord","mmoms":"-9 695 225 kr","umoms":"-7 756 180 kr","db":"-2 038 976 kr","dg":"-2.2%","antord":"- 8 308","prord":"  50 kr"},{"butikk":"Larvik","mmoms":"-6 971 165 kr","umoms":"-5 576 932 kr","db":"-1 427 101 kr","dg":"-1.5%","antord":"- 5 617","prord":"-  13 kr"},{"butikk":"Totalt","mmoms":"-72 145 344 kr","umoms":"-57 716 275 kr","db":"-14 627 472 kr","dg":"-1.9%","antord":"- 57 301","prord":"  5 kr"}]
