[{"butikk":"Brødr. Berg Stenindustri AS avd. Skien","mmoms":"1 198 010 kr","umoms":" 958 408 kr","antord":" 1 124","prord":"-  48 kr"},{"butikk":"Brødr. Berg Stenindustri AS avd. Porsgrunn","mmoms":"- 180 883 kr","umoms":"- 144 706 kr","antord":"  174","prord":"-  164 kr"},{"butikk":"Megaflis Sørlandsparken AS","mmoms":" 615 999 kr","umoms":" 492 799 kr","antord":"  712","prord":"-  61 kr"},{"butikk":"Megaflis Tønsberg AS","mmoms":" 637 079 kr","umoms":" 509 664 kr","antord":"  423","prord":"  30 kr"},{"butikk":"Megaflis Agderparken AS","mmoms":"1 410 932 kr","umoms":"1 128 746 kr","antord":" 1 643","prord":"-  54 kr"},{"butikk":"Megaflis Sandefjord AS","mmoms":"1 169 173 kr","umoms":" 935 338 kr","antord":"  828","prord":"  62 kr"},{"butikk":"Megaflis Larvik AS","mmoms":" 883 703 kr","umoms":" 706 963 kr","antord":"  764","prord":"-  5 kr"},{"butikk":"Totalt","mmoms":"5 734 013 kr","umoms":"4 587 211 kr","antord":" 5 668","prord":"-  22 kr"}]
