[{"butikk":"Brødr. Berg Stenindustri AS avd. Skien","mmoms":"1 056 288 kr","umoms":" 845 030 kr","antord":"  367","prord":"  99 kr"},{"butikk":"Brødr. Berg Stenindustri AS avd. Porsgrunn","mmoms":"- 81 524 kr","umoms":"- 65 219 kr","antord":"-  286","prord":"  77 kr"},{"butikk":"Megaflis Sørlandsparken AS","mmoms":" 413 115 kr","umoms":" 330 492 kr","antord":"-  5","prord":"  94 kr"},{"butikk":"Megaflis Tønsberg AS","mmoms":"- 15 682 kr","umoms":"- 12 546 kr","antord":"-  544","prord":"  91 kr"},{"butikk":"Megaflis Agderparken AS","mmoms":"1 585 351 kr","umoms":"1 268 281 kr","antord":"  540","prord":"  147 kr"},{"butikk":"Megaflis Sandefjord AS","mmoms":" 777 168 kr","umoms":" 621 734 kr","antord":"  415","prord":"  65 kr"},{"butikk":"Megaflis Larvik AS","mmoms":" 680 674 kr","umoms":" 544 539 kr","antord":"  397","prord":"  66 kr"},{"butikk":"Totalt","mmoms":"4 415 390 kr","umoms":"3 532 312 kr","antord":"  884","prord":"  100 kr"}]
