[{"butikk":"Brødr. Berg Stenindustri AS avd. Skien","mmoms":" 872 077 kr","umoms":" 697 661 kr","db":" 205 327 kr","dg":"1.55%","antord":"  572","prord":"  33 kr"},{"butikk":"Brødr. Berg Stenindustri AS avd. Porsgrunn","mmoms":" 196 938 kr","umoms":" 157 550 kr","db":" 55 867 kr","dg":"4.66%","antord":"  197","prord":"  49 kr"},{"butikk":"Megaflis Sørlandsparken AS","mmoms":" 314 288 kr","umoms":" 251 430 kr","db":" 128 421 kr","dg":"4.39%","antord":"  327","prord":"-  113 kr"},{"butikk":"Megaflis Tønsberg AS","mmoms":" 353 594 kr","umoms":" 282 875 kr","db":" 133 938 kr","dg":"3.37%","antord":"  329","prord":"-  5 kr"},{"butikk":"Megaflis Agderparken AS","mmoms":"1 019 541 kr","umoms":" 815 633 kr","db":" 254 444 kr","dg":"1.88%","antord":"  668","prord":"  147 kr"},{"butikk":"Megaflis Sandefjord AS","mmoms":" 341 508 kr","umoms":" 273 206 kr","db":" 87 311 kr","dg":"0.92%","antord":"  291","prord":"  12 kr"},{"butikk":"Megaflis Larvik AS","mmoms":" 387 353 kr","umoms":" 309 882 kr","db":" 83 683 kr","dg":"-0.05%","antord":"  322","prord":"  16 kr"},{"butikk":"Totalt","mmoms":"3 485 298 kr","umoms":"2 788 238 kr","db":" 948 990 kr","dg":"2.29%","antord":" 2 706","prord":"  26 kr"}]
