[{"butikk":"Brødr. Berg Stenindustri AS avd. Skien","ERPHostCompanyNo":1,"WarehouseNo":1,"mmoms":"5 681 248 kr","umoms":"4 544 998 kr","db":"1 161 977 kr","dg":"25.57%","antord":" 4 490","prord":" 1 265 kr"},{"butikk":"Brødr. Berg Stenindustri AS avd. Porsgrunn","ERPHostCompanyNo":1,"WarehouseNo":2,"mmoms":"1 119 015 kr","umoms":" 895 212 kr","db":" 215 747 kr","dg":"24.10%","antord":" 1 374","prord":"  814 kr"},{"butikk":"Megaflis Sørlandsparken AS","ERPHostCompanyNo":2,"WarehouseNo":1,"mmoms":"3 324 411 kr","umoms":"2 659 529 kr","db":" 689 787 kr","dg":"25.94%","antord":" 2 776","prord":" 1 198 kr"},{"butikk":"Megaflis Tønsberg AS","ERPHostCompanyNo":3,"WarehouseNo":1,"mmoms":"4 976 229 kr","umoms":"3 980 983 kr","db":"1 082 296 kr","dg":"27.19%","antord":" 4 348","prord":" 1 144 kr"},{"butikk":"Megaflis Agderparken AS","ERPHostCompanyNo":4,"WarehouseNo":1,"mmoms":"4 956 712 kr","umoms":"3 965 370 kr","db":"1 032 206 kr","dg":"26.03%","antord":" 4 410","prord":" 1 124 kr"},{"butikk":"Megaflis Sandefjord AS","ERPHostCompanyNo":10,"WarehouseNo":1,"mmoms":"3 472 483 kr","umoms":"2 777 986 kr","db":" 751 149 kr","dg":"27.04%","antord":" 3 290","prord":" 1 055 kr"},{"butikk":"Megaflis Larvik AS","ERPHostCompanyNo":16,"WarehouseNo":1,"mmoms":"2 726 401 kr","umoms":"2 181 121 kr","db":" 542 277 kr","dg":"24.86%","antord":" 2 408","prord":" 1 132 kr"},{"butikk":"Totalt","ERPHostCompanyNo":9999,"WarehouseNo":9999,"mmoms":"26 256 499 kr","umoms":"21 005 199 kr","db":"5 475 440 kr","dg":"26.07%","antord":" 23 096","prord":" 1 137 kr"}]
