[{"butikk":"Skien","mmoms":"-48 392 562 kr","umoms":"-38 714 050 kr","db":"-9 218 275 kr","dg":"-3.8%","antord":"- 34 897","prord":"-  47 kr"},{"butikk":"Porsgrunn","mmoms":"-8 960 992 kr","umoms":"-7 168 793 kr","db":"-1 694 180 kr","dg":"-0.6%","antord":"- 10 794","prord":"-  103 kr"},{"butikk":"Kristiansand","mmoms":"-32 912 144 kr","umoms":"-26 329 715 kr","db":"-6 731 201 kr","dg":"-8.0%","antord":"- 26 123","prord":"  21 kr"},{"butikk":"Tønsberg","mmoms":"-37 409 192 kr","umoms":"-29 927 354 kr","db":"-7 436 210 kr","dg":"-5.1%","antord":"- 31 805","prord":"-  130 kr"},{"butikk":"Arendal","mmoms":"-48 185 902 kr","umoms":"-38 548 722 kr","db":"-9 834 381 kr","dg":"-3.5%","antord":"- 40 985","prord":"-  163 kr"},{"butikk":"Sandefjord","mmoms":"-31 209 667 kr","umoms":"-24 967 733 kr","db":"-6 525 686 kr","dg":"-6.3%","antord":"- 27 229","prord":"-  145 kr"},{"butikk":"Larvik","mmoms":"-23 971 829 kr","umoms":"-19 177 464 kr","db":"-4 742 661 kr","dg":"-5.8%","antord":"- 18 897","prord":"-  384 kr"},{"butikk":"Totalt","mmoms":"-231 042 289 kr","umoms":"-184 833 831 kr","db":"-46 182 594 kr","dg":"-5.0%","antord":"- 190 730","prord":"-  128 kr"}]
