[{"butikk":"Skien","Klient":0,"mmoms":"6 280 764 kr","umoms":"5 024 611 kr","db":" 823 793 kr","dg":"16.4%","antord":" 3 288","prord":" 1 910 kr"},{"butikk":"Porsgrunn","Klient":1,"mmoms":" 748 084 kr","umoms":" 598 468 kr","db":" 101 265 kr","dg":"16.9%","antord":"  725","prord":" 1 032 kr"},{"butikk":"Kristiansand","Klient":2,"mmoms":"4 306 845 kr","umoms":"3 445 476 kr","db":" 527 525 kr","dg":"15.3%","antord":" 2 306","prord":" 1 868 kr"},{"butikk":"Tønsberg","Klient":3,"mmoms":"4 194 706 kr","umoms":"3 355 764 kr","db":" 576 979 kr","dg":"17.2%","antord":" 2 934","prord":" 1 430 kr"},{"butikk":"Arendal","Klient":4,"mmoms":"5 068 731 kr","umoms":"4 054 985 kr","db":" 718 485 kr","dg":"17.7%","antord":" 3 374","prord":" 1 502 kr"},{"butikk":"Sandefjord","Klient":5,"mmoms":"3 366 115 kr","umoms":"2 692 892 kr","db":" 473 308 kr","dg":"17.6%","antord":" 2 350","prord":" 1 432 kr"},{"butikk":"Larvik","Klient":6,"mmoms":"2 454 830 kr","umoms":"1 963 864 kr","db":" 367 037 kr","dg":"18.7%","antord":" 1 732","prord":" 1 417 kr"},{"butikk":"Totalt","Klient":9999,"mmoms":"26 420 752 kr","umoms":"21 136 602 kr","db":"3 588 233 kr","dg":"17.0%","antord":" 16 710","prord":" 1 581 kr"}]
