[{"butikk":"Brødr. Berg Stenindustri AS avd. Skien","ERPHostCompanyNo":1,"WarehouseNo":1,"mmoms":"2 323 611 kr","umoms":"1 858 889 kr","db":" 481 787 kr","dg":"25.92%","antord":" 1 804","prord":" 1 288 kr"},{"butikk":"Brødr. Berg Stenindustri AS avd. Porsgrunn","ERPHostCompanyNo":1,"WarehouseNo":2,"mmoms":" 410 383 kr","umoms":" 328 306 kr","db":" 134 661 kr","dg":"41.02%","antord":"  500","prord":"  821 kr"},{"butikk":"Megaflis Sørlandsparken AS","ERPHostCompanyNo":2,"WarehouseNo":1,"mmoms":"1 490 069 kr","umoms":"1 192 055 kr","db":" 390 913 kr","dg":"32.79%","antord":" 1 225","prord":" 1 216 kr"},{"butikk":"Megaflis Tønsberg AS","ERPHostCompanyNo":3,"WarehouseNo":1,"mmoms":"1 531 459 kr","umoms":"1 225 167 kr","db":" 356 150 kr","dg":"29.07%","antord":" 1 250","prord":" 1 225 kr"},{"butikk":"Megaflis Agderparken AS","ERPHostCompanyNo":4,"WarehouseNo":1,"mmoms":"2 541 626 kr","umoms":"2 033 301 kr","db":" 588 028 kr","dg":"28.92%","antord":" 2 043","prord":" 1 244 kr"},{"butikk":"Megaflis Sandefjord AS","ERPHostCompanyNo":10,"WarehouseNo":1,"mmoms":"1 901 600 kr","umoms":"1 521 280 kr","db":" 449 769 kr","dg":"29.57%","antord":" 1 451","prord":" 1 311 kr"},{"butikk":"Megaflis Larvik AS","ERPHostCompanyNo":16,"WarehouseNo":1,"mmoms":"1 277 254 kr","umoms":"1 021 803 kr","db":" 258 634 kr","dg":"25.31%","antord":" 1 002","prord":" 1 275 kr"},{"butikk":"Totalt","ERPHostCompanyNo":9999,"WarehouseNo":9999,"mmoms":"11 476 001 kr","umoms":"9 180 801 kr","db":"2 659 941 kr","dg":"28.97%","antord":" 9 275","prord":" 1 237 kr"}]
