[{"butikk":"Brødr. Berg Stenindustri AS avd. Skien","mmoms":" 862 295 kr","umoms":" 689 836 kr","db":" 561 530 kr","dg":"10.18%","antord":"  655","prord":"-  14 kr"},{"butikk":"Brødr. Berg Stenindustri AS avd. Porsgrunn","mmoms":"- 292 328 kr","umoms":"- 233 862 kr","db":" 458 934 kr","dg":"82.59%","antord":"  49","prord":"-  354 kr"},{"butikk":"Megaflis Sørlandsparken AS","mmoms":" 504 605 kr","umoms":" 403 684 kr","db":"1 761 191 kr","dg":"68.30%","antord":"  441","prord":"-  22 kr"},{"butikk":"Megaflis Tønsberg AS","mmoms":"- 925 113 kr","umoms":"- 740 090 kr","db":"- 82 491 kr","dg":"4.47%","antord":"- 1 291","prord":"  247 kr"},{"butikk":"Megaflis Agderparken AS","mmoms":"1 541 191 kr","umoms":"1 232 953 kr","db":"1 207 772 kr","dg":"22.71%","antord":" 1 073","prord":"  81 kr"},{"butikk":"Megaflis Sandefjord AS","mmoms":"1 243 533 kr","umoms":" 994 826 kr","db":" 361 313 kr","dg":"3.09%","antord":"  426","prord":"  294 kr"},{"butikk":"Megaflis Larvik AS","mmoms":"1 184 830 kr","umoms":" 947 864 kr","db":" 206 789 kr","dg":"-2.34%","antord":"  431","prord":"  406 kr"},{"butikk":"Totalt","mmoms":"4 119 014 kr","umoms":"3 295 211 kr","db":"4 475 037 kr","dg":"20.32%","antord":" 1 784","prord":"  117 kr"}]
