[{"selger":"Helen Rougnø","Beløp":" 160 648 kr","butikk":"Tønsberg"},{"selger":"Christoffer Fosstvedt","Beløp":" 125 466 kr","butikk":"BrBerg"},{"selger":"Torstein S","Beløp":" 114 744 kr","butikk":"Arendal"},{"selger":"Kristine Martinsen","Beløp":" 112 410 kr","butikk":"Arendal"},{"selger":"Heidi Kihle Lindvig","Beløp":" 107 471 kr","butikk":"BrBerg"},{"selger":"James Michael McGurty","Beløp":" 93 886 kr","butikk":"BrBerg"},{"selger":"Jonas Garstad","Beløp":" 86 469 kr","butikk":"BrBerg"},{"selger":"Elin Eilefsen","Beløp":" 84 469 kr","butikk":"Larvik"},{"selger":"Tom Richard Ekeberg","Beløp":" 83 505 kr","butikk":"Larvik"},{"selger":"Andreas Gravdahl","Beløp":" 82 317 kr","butikk":"Tønsberg"}]
