[{"butikk":"Brødr. Berg Stenindustri AS avd. Skien","ERPHostCompanyNo":1,"WarehouseNo":1,"mmoms":"5 511 257 kr","umoms":"4 409 006 kr","antord":" 4 296","prord":" 1 283 kr"},{"butikk":"Brødr. Berg Stenindustri AS avd. Porsgrunn","ERPHostCompanyNo":1,"WarehouseNo":2,"mmoms":"1 248 476 kr","umoms":" 998 781 kr","antord":" 1 388","prord":"  899 kr"},{"butikk":"Megaflis Sørlandsparken AS","ERPHostCompanyNo":2,"WarehouseNo":1,"mmoms":"3 607 861 kr","umoms":"2 886 289 kr","antord":" 3 002","prord":" 1 202 kr"},{"butikk":"Megaflis Tønsberg AS","ERPHostCompanyNo":3,"WarehouseNo":1,"mmoms":"4 435 904 kr","umoms":"3 548 723 kr","antord":" 4 108","prord":" 1 080 kr"},{"butikk":"Megaflis Agderparken AS","ERPHostCompanyNo":4,"WarehouseNo":1,"mmoms":"5 593 424 kr","umoms":"4 474 739 kr","antord":" 4 728","prord":" 1 183 kr"},{"butikk":"Megaflis Sandefjord AS","ERPHostCompanyNo":10,"WarehouseNo":1,"mmoms":"3 848 343 kr","umoms":"3 078 674 kr","antord":" 3 481","prord":" 1 106 kr"},{"butikk":"Megaflis Larvik AS","ERPHostCompanyNo":16,"WarehouseNo":1,"mmoms":"2 828 810 kr","umoms":"2 263 048 kr","antord":" 2 371","prord":" 1 193 kr"},{"butikk":"Totalt","ERPHostCompanyNo":9999,"WarehouseNo":9999,"mmoms":"27 074 075 kr","umoms":"21 659 260 kr","antord":" 23 374","prord":" 1 158 kr"}]
