[{"butikk":"Brødr. Berg Stenindustri AS avd. Skien","mmoms":"- 56 936 kr","umoms":"- 45 548 kr","antord":"  126","prord":"-  34 kr"},{"butikk":"Brødr. Berg Stenindustri AS avd. Porsgrunn","mmoms":"- 662 630 kr","umoms":"- 530 104 kr","antord":"-  361","prord":"-  165 kr"},{"butikk":"Megaflis Sørlandsparken AS","mmoms":" 2 380 kr","umoms":" 1 904 kr","antord":"-  32","prord":"  9 kr"},{"butikk":"Megaflis Tønsberg AS","mmoms":"- 802 697 kr","umoms":"- 642 158 kr","antord":"-  776","prord":"  3 kr"},{"butikk":"Megaflis Agderparken AS","mmoms":" 312 624 kr","umoms":" 250 100 kr","antord":"  680","prord":"-  54 kr"},{"butikk":"Megaflis Sandefjord AS","mmoms":"- 49 775 kr","umoms":"- 39 820 kr","antord":"-  101","prord":"  10 kr"},{"butikk":"Megaflis Larvik AS","mmoms":" 328 136 kr","umoms":" 262 509 kr","antord":"  173","prord":"  39 kr"},{"butikk":"Totalt","mmoms":"- 928 897 kr","umoms":"- 743 118 kr","antord":"-  291","prord":"-  17 kr"}]
