[{"butikk":"Brødr. Berg Stenindustri AS avd. Skien","ERPHostCompanyNo":1,"WarehouseNo":1,"mmoms":"8 781 144 kr","umoms":"7 024 915 kr","db":"1 701 678 kr","dg":"24.22%","antord":" 6 320","prord":" 1 389 kr"},{"butikk":"Brødr. Berg Stenindustri AS avd. Porsgrunn","ERPHostCompanyNo":1,"WarehouseNo":2,"mmoms":"1 955 812 kr","umoms":"1 564 649 kr","db":" 341 796 kr","dg":"21.84%","antord":" 2 022","prord":"  967 kr"},{"butikk":"Megaflis Sørlandsparken AS","ERPHostCompanyNo":2,"WarehouseNo":1,"mmoms":"5 621 197 kr","umoms":"4 496 958 kr","db":"1 095 901 kr","dg":"24.37%","antord":" 4 079","prord":" 1 378 kr"},{"butikk":"Megaflis Tønsberg AS","ERPHostCompanyNo":3,"WarehouseNo":1,"mmoms":"6 540 539 kr","umoms":"5 232 431 kr","db":"1 340 671 kr","dg":"25.62%","antord":" 6 127","prord":" 1 067 kr"},{"butikk":"Megaflis Agderparken AS","ERPHostCompanyNo":4,"WarehouseNo":1,"mmoms":"7 051 525 kr","umoms":"5 641 220 kr","db":"1 462 157 kr","dg":"25.92%","antord":" 6 238","prord":" 1 130 kr"},{"butikk":"Megaflis Sandefjord AS","ERPHostCompanyNo":10,"WarehouseNo":1,"mmoms":"4 833 527 kr","umoms":"3 866 822 kr","db":" 967 798 kr","dg":"25.03%","antord":" 4 724","prord":" 1 023 kr"},{"butikk":"Megaflis Larvik AS","ERPHostCompanyNo":16,"WarehouseNo":1,"mmoms":"3 540 185 kr","umoms":"2 832 148 kr","db":" 681 395 kr","dg":"24.06%","antord":" 3 197","prord":" 1 107 kr"},{"butikk":"Totalt","ERPHostCompanyNo":9999,"WarehouseNo":9999,"mmoms":"38 323 959 kr","umoms":"30 659 167 kr","db":"7 591 407 kr","dg":"24.76%","antord":" 32 708","prord":" 1 172 kr"}]
