[{"selger":"Linn Kristine Terjesen","Beløp":" 961 689 kr","butikk":"Arendal"},{"selger":"Heidi Kihle Lindvig","Beløp":" 859 530 kr","butikk":"BrBerg"},{"selger":"Erica Hegge Nilsen","Beløp":" 825 249 kr","butikk":"Sandefjord"},{"selger":"Hans Kristian Nenset","Beløp":" 784 590 kr","butikk":"BrBerg"},{"selger":"Bertil Tangen","Beløp":" 764 867 kr","butikk":"Sandefjord"},{"selger":"Helen Rougnø","Beløp":" 731 843 kr","butikk":"Tønsberg"},{"selger":"Fredrik Frost Pettersen","Beløp":" 727 009 kr","butikk":"Tønsberg"},{"selger":"Nadia Tveit Ramse","Beløp":" 683 840 kr","butikk":"Arendal"},{"selger":"James Michael McGurty","Beløp":" 646 720 kr","butikk":"BrBerg"},{"selger":"Andreas Gravdahl","Beløp":" 641 753 kr","butikk":"Tønsberg"}]
