[{"butikk":"Skien","Klient":0,"mmoms":"7 450 363 kr","umoms":"5 960 290 kr","db":"1 231 580 kr","dg":"20.7%","antord":" 5 322","prord":" 1 400 kr"},{"butikk":"Porsgrunn","Klient":1,"mmoms":"1 047 098 kr","umoms":" 837 679 kr","db":" 164 100 kr","dg":"19.6%","antord":" 1 429","prord":"  733 kr"},{"butikk":"Kristiansand","Klient":2,"mmoms":"4 854 964 kr","umoms":"3 883 971 kr","db":" 757 525 kr","dg":"19.5%","antord":" 3 785","prord":" 1 283 kr"},{"butikk":"Tønsberg","Klient":3,"mmoms":"5 535 400 kr","umoms":"4 428 320 kr","db":" 904 813 kr","dg":"20.4%","antord":" 4 867","prord":" 1 137 kr"},{"butikk":"Arendal","Klient":4,"mmoms":"7 308 938 kr","umoms":"5 847 150 kr","db":"1 132 114 kr","dg":"19.4%","antord":" 5 932","prord":" 1 232 kr"},{"butikk":"Sandefjord","Klient":5,"mmoms":"4 548 225 kr","umoms":"3 638 580 kr","db":" 662 019 kr","dg":"18.2%","antord":" 4 014","prord":" 1 133 kr"},{"butikk":"Larvik","Klient":6,"mmoms":"3 343 140 kr","umoms":"2 674 512 kr","db":" 511 859 kr","dg":"19.1%","antord":" 3 034","prord":" 1 102 kr"},{"butikk":"Totalt","Klient":9999,"mmoms":"34 088 128 kr","umoms":"27 270 503 kr","db":"5 364 009 kr","dg":"19.7%","antord":" 28 383","prord":" 1 201 kr"}]
