[{"butikk":"Brødr. Berg Stenindustri AS avd. Skien","ERPHostCompanyNo":1,"WarehouseNo":1,"mmoms":"1 406 891 kr","umoms":"1 125 513 kr","antord":" 1 136","prord":" 1 238 kr"},{"butikk":"Brødr. Berg Stenindustri AS avd. Porsgrunn","ERPHostCompanyNo":1,"WarehouseNo":2,"mmoms":" 333 111 kr","umoms":" 266 489 kr","antord":"  373","prord":"  893 kr"},{"butikk":"Megaflis Sørlandsparken AS","ERPHostCompanyNo":2,"WarehouseNo":1,"mmoms":"1 011 116 kr","umoms":" 808 893 kr","antord":"  852","prord":" 1 187 kr"},{"butikk":"Megaflis Tønsberg AS","ERPHostCompanyNo":3,"WarehouseNo":1,"mmoms":"1 316 322 kr","umoms":"1 053 057 kr","antord":" 1 060","prord":" 1 242 kr"},{"butikk":"Megaflis Agderparken AS","ERPHostCompanyNo":4,"WarehouseNo":1,"mmoms":"1 422 914 kr","umoms":"1 138 331 kr","antord":" 1 419","prord":" 1 003 kr"},{"butikk":"Megaflis Sandefjord AS","ERPHostCompanyNo":10,"WarehouseNo":1,"mmoms":" 918 701 kr","umoms":" 734 961 kr","antord":"  926","prord":"  992 kr"},{"butikk":"Megaflis Larvik AS","ERPHostCompanyNo":16,"WarehouseNo":1,"mmoms":" 732 212 kr","umoms":" 585 770 kr","antord":"  692","prord":" 1 058 kr"},{"butikk":"Totalt","ERPHostCompanyNo":9999,"WarehouseNo":9999,"mmoms":"7 141 266 kr","umoms":"5 713 013 kr","antord":" 6 458","prord":" 1 106 kr"}]
