[{"butikk":"Skien","mmoms":"-64 442 119 kr","umoms":"-51 553 695 kr","db":"-12 096 135 kr","dg":"-4.6%","antord":"- 47 522","prord":"  151 kr"},{"butikk":"Porsgrunn","mmoms":"-12 384 946 kr","umoms":"-9 907 957 kr","db":"-2 303 237 kr","dg":"-7.3%","antord":"- 15 147","prord":"-  173 kr"},{"butikk":"Kristiansand","mmoms":"-43 856 543 kr","umoms":"-35 085 235 kr","db":"-8 725 127 kr","dg":"-5.8%","antord":"- 34 851","prord":"  161 kr"},{"butikk":"Tønsberg","mmoms":"-49 017 455 kr","umoms":"-39 213 964 kr","db":"-9 576 950 kr","dg":"-2.5%","antord":"- 43 106","prord":"  140 kr"},{"butikk":"Arendal","mmoms":"-63 276 846 kr","umoms":"-50 621 476 kr","db":"-12 739 496 kr","dg":"-2.8%","antord":"- 54 759","prord":"-  44 kr"},{"butikk":"Sandefjord","mmoms":"-40 812 161 kr","umoms":"-32 649 729 kr","db":"-8 353 671 kr","dg":"-4.7%","antord":"- 36 764","prord":"  36 kr"},{"butikk":"Larvik","mmoms":"-31 152 957 kr","umoms":"-24 922 366 kr","db":"-6 071 011 kr","dg":"-4.2%","antord":"- 25 848","prord":"  65 kr"},{"butikk":"Totalt","mmoms":"-304 943 028 kr","umoms":"-243 954 422 kr","db":"-59 865 628 kr","dg":"-4.1%","antord":"- 257 996","prord":"  95 kr"}]
